{"meta": {"triggerEventLog": {"id": "NL54L5-2026-07-14-TKT"}, "version": "3.5.0"}, "processedTicket": {"id": "0149016324291-2026-07-14", "version": "1759520979000", "latestEvent": {"code": "130", "dateTimeGMT": "2026-07-14T20:00:00Z"}, "documentType": "T", "primaryDocumentNumber": "0149016324291", "documentNumbers": ["0149016324291"], "numberOfBooklets": 1, "issuanceLocalDate": "2026-07-14", "issuanceType": "F", "validatingCarrierCode": "AC", "validatingCarrierRecordLocator": "NL54L5", "pnrReferences": [{"systemId": "AC", "recordLocator": "NL54L5"}, {"systemId": "1A", "recordLocator": "NL54L5"}], "traveler": {"name": {"firstName": "AMBROSE", "lastName": "GREENENMARSH"}, "passengerTypeCode": "ADT"}, "price": {"currency": "CAD", "total": "612.00"}, "coupons": [{"id": "0149016324291-2026-07-14-1", "number": 1, "status": "OPEN_FOR_USE", "fareBasisCode": "YFLEX"}]}, "events": {"recordDomain": "TICKET", "recordId": "0149016324291-2026-07-14", "originFeedTimeStamp": "2026-07-14T19:49:38", "events": [{"origin": "COMPARISON", "eventType": "CREATED"}]}}