{"events": {"events": [{"origin": "COMPARISON", "currentPath": "/ticketingReferences", "eventType": "CREATED"}], "recordId": "GE7YP8-2026-07-10"}, "meta": {"subscribedCustomerTrigger": {"triggerEventName": "TicketingRefCreated"}, "triggerEventLog": {"id": "GE7YP8-2026-07-10-CR"}}, "processedPnr": {"id": "GE7YP8-2026-07-10", "bookingIdentifier": "GE7YP8", "version": "1", "creation": {"dateTime": "2026-07-10T06:00:00Z", "pointOfSale": {"office": {"id": "YULAC010V", "systemCode": "1A", "iataNumber": "01424012", "agentType": "AIRLINE"}}}, "lastModification": {"dateTime": "2026-07-10T06:00:00Z"}, "pnrReferences": [{"systemId": "1A", "recordLocator": "GE7YP8"}], "travelers": [{"type": "stakeholder", "id": "GE7YP8-2026-07-10-PT-1", "names": [{"firstName": "BEATRIX", "lastName": "NETHERBY"}], "gender": "UNKNOWN", "passengerTypeCode": "ADT", "identityDocuments": [{"code": "DOCS", "subType": "SPECIAL_SERVICE_REQUEST", "status": "HK", "document": {"gender": "UNKNOWN", "birthDate": "1986-04-23", "name": {"firstName": "BEATRIX", "lastName": "NETHERBY"}, "countryOfResidence": "IL"}, "text": "////23APR86/U//NETHERBY/BEATRIX"}], "contacts": {"collection": [{"type": "contact", "id": "GE7YP8-2026-07-10-OT-23", "ref": "processedPnr.contacts"}]}}], "contacts": [{"type": "contact", "id": "GE7YP8-2026-07-10-OT-23", "email": {"address": "lahiru@ae-qa1-aircanada.mailinator.com"}, "language": "EN", "purpose": ["NOTIFICATION"], "travelers": {"collection": [{"id": "GE7YP8-2026-07-10-PT-1", "ref": "processedPnr.travelers"}]}}], "products": [{"id": "GE7YP8-2026-07-10-ST-1", "subType": "AIR", "airSegment": {"number": "8002", "carrierCode": "AC", "departure": {"iataCode": "YYZ", "localDateTime": "2026-07-10T08:00:00"}, "arrival": {"iataCode": "TLV", "localDateTime": "2026-07-10T11:00:00"}, "status": "HK", "cabinClass": "Y"}}], "ticketingReferences": [{"id": "TKT-REF-1", "documents": [{"primaryDocumentNumber": "0149013244837", "issuanceLocalDate": "2026-07-10", "status": "ISSUED", "fareCalculation": "YYZ AC LHR 420.00", "fareCalculationMode": "AUTO", "endorsementFreeFlow": "NONREF", "displayedFormsOfPayment": [{"method": "CREDIT_CARD", "fopIndicator": "CC", "paymentCard": {"vendorCode": "VI"}, "authorization": {"approvalCode": "123456"}}], "coupons": [{"number": "1", "status": "O", "fareBasisCode": "YFLEX", "soldSegment": {"flightNumber": "8002", "departure": {"iataCode": "YYZ"}, "arrival": {"iataCode": "TLV"}, "carrierCode": "AC"}}], "issuingOriginator": {"author": {"carrier": {"IATANumber": "01424012"}, "deliveringSystem": {"systemIdentification": "1A"}, "officeId": "YULAC010V"}}}]}], "latestEvent": {"code": "TKTREF_CREATED", "dateTimeGMT": "2026-07-10T06:00:00Z"}}}