{"meta": {"triggerEventLog": {"id": "GE7YP8-2026-07-10-TKT"}, "version": "3.5.0"}, "processedTicket": {"id": "0149013244837-2026-07-10", "version": "1759520979000", "latestEvent": {"code": "130", "dateTimeGMT": "2026-07-10T20:00:00Z"}, "documentType": "T", "primaryDocumentNumber": "0149013244837", "documentNumbers": ["0149013244837"], "numberOfBooklets": 1, "issuanceLocalDate": "2026-07-10", "issuanceType": "F", "validatingCarrierCode": "AC", "validatingCarrierRecordLocator": "GE7YP8", "pnrReferences": [{"systemId": "AC", "recordLocator": "GE7YP8"}, {"systemId": "1A", "recordLocator": "GE7YP8"}], "traveler": {"name": {"firstName": "BEATRIX", "lastName": "NETHERBY"}, "passengerTypeCode": "ADT"}, "price": {"currency": "CAD", "total": "612.00"}, "coupons": [{"id": "0149013244837-2026-07-10-1", "number": 1, "status": "OPEN_FOR_USE", "fareBasisCode": "YFLEX"}]}, "events": {"recordDomain": "TICKET", "recordId": "0149013244837-2026-07-10", "originFeedTimeStamp": "2026-07-10T19:49:38", "events": [{"origin": "COMPARISON", "eventType": "CREATED"}]}}